setup.py
funbox/__init__.py
funbox/cmdline_parsing.py
funbox/csv_records.py
funbox/dates.py
funbox/flogic.py
funbox/func.py
funbox/itertools_compat.py
funbox/lists.py
funbox/mappings.py
funbox/maybe.py
funbox/misc.py
funbox/once.py
funbox/op.py
funbox/pairs.py
funbox/passthrough.py
funbox/strings.py
funbox/validation.py
funbox.egg-info/PKG-INFO
funbox.egg-info/SOURCES.txt
funbox.egg-info/dependency_links.txt
funbox.egg-info/requires.txt
funbox.egg-info/top_level.txt
funbox/iterators/__init__.py
funbox/iterators/ordered.py