Metadata-Version: 1.0
Name: funbox
Version: 0.10
Summary: Functional Toolbox
Home-page: https://github.com/nmbooker/python-funbox
Author: Nick Booker
Author-email: UNKNOWN
License: MIT
Platform: UNKNOWN
